README.md
setup.py
midi_simplifier/Chord.py
midi_simplifier/Note.py
midi_simplifier/Sequence.py
midi_simplifier/Simplifier.py
midi_simplifier/__init__.py
midi_simplifier.egg-info/PKG-INFO
midi_simplifier.egg-info/SOURCES.txt
midi_simplifier.egg-info/dependency_links.txt
midi_simplifier.egg-info/requires.txt
midi_simplifier.egg-info/top_level.txt
midi_simplifier/inner_classes/Chord__.py
midi_simplifier/inner_classes/Creator.py
midi_simplifier/inner_classes/Note__.py
midi_simplifier/inner_classes/ScaleDetector.py
midi_simplifier/inner_classes/Track.py
midi_simplifier/inner_classes/__init__.py
midi_simplifier/utils/__init__.py
midi_simplifier/utils/decorators.py
midi_simplifier/utils/helpers.py
midi_simplifier/utils/utils.py