Metadata-Version: 2.1
Name: midi-simplifier
Version: 0.5.0
Summary: a Python midi utility
Home-page: UNKNOWN
Author: danielnachumdev (Daniel Nachum)
Author-email: <danielnachumdev@gmail.com>
License: UNKNOWN
Keywords: midi,python,note,chord,scale
Platform: UNKNOWN
Classifier: Intended Audience :: Developers
Classifier: Programming Language :: Python :: 3
Classifier: Operating System :: Unix
Classifier: Operating System :: MacOS :: MacOS X
Classifier: Operating System :: Microsoft :: Windows
